{
  "investigadores": [
    {
      "id": "INV001",
      "nombre": "Dra. Carmen Lucía Ospina",
      "titulo": "PhD en Ciencias de la Educación",
      "institucion": "Universidad de Nariño",
      "departamento": "Facultad de Educación",
      "areas_expertise": ["educación rural", "competencias digitales", "pedagogía crítica", "innovación educativa"],
      "experiencia_convocatorias": ["MGA", "MINCIENCIAS", "ERASMUS"],
      "proyectos_anteriores": 8,
      "publicaciones_indexadas": 12,
      "idiomas": ["español", "inglés"],
      "disponibilidad": "tiempo_parcial",
      "email": "cospina@udenar.edu.co"
    },
    {
      "id": "INV002",
      "nombre": "Dr. Andrés Felipe Muñoz",
      "titulo": "PhD en Ingeniería de Sistemas",
      "institucion": "Universidad Nacional de Colombia",
      "departamento": "Departamento de Ingeniería de Sistemas",
      "areas_expertise": ["inteligencia artificial", "tecnología educativa", "desarrollo de software", "ciencia de datos"],
      "experiencia_convocatorias": ["MINCIENCIAS", "BID", "HORIZONTE"],
      "proyectos_anteriores": 15,
      "publicaciones_indexadas": 28,
      "idiomas": ["español", "inglés", "portugués"],
      "disponibilidad": "tiempo_completo",
      "email": "afmunoz@unal.edu.co"
    },
    {
      "id": "INV003",
      "nombre": "Mg. Sandra Patricia Guerrero",
      "titulo": "Magíster en Desarrollo Rural",
      "institucion": "Universidad del Cauca",
      "departamento": "Facultad de Ciencias Agrarias",
      "areas_expertise": ["desarrollo rural", "comunidades campesinas", "seguridad alimentaria", "gestión territorial"],
      "experiencia_convocatorias": ["MGA", "BID", "ZOPP"],
      "proyectos_anteriores": 6,
      "publicaciones_indexadas": 4,
      "idiomas": ["español"],
      "disponibilidad": "tiempo_parcial",
      "email": "spguerrero@unicauca.edu.co"
    },
    {
      "id": "INV004",
      "nombre": "Dr. Jorge Iván Castellanos",
      "titulo": "PhD en Ciencias Ambientales",
      "institucion": "Universidad de Antioquia",
      "departamento": "Instituto de Estudios Regionales",
      "areas_expertise": ["impacto ambiental", "cambio climático", "gestión de riesgos", "desarrollo sostenible"],
      "experiencia_convocatorias": ["MGA", "BID", "HORIZONTE", "MINCIENCIAS"],
      "proyectos_anteriores": 11,
      "publicaciones_indexadas": 19,
      "idiomas": ["español", "inglés", "francés"],
      "disponibilidad": "tiempo_completo",
      "email": "jicastellanos@udea.edu.co"
    },
    {
      "id": "INV005",
      "nombre": "Dra. María Fernanda Ríos",
      "titulo": "PhD en Economía del Desarrollo",
      "institucion": "Universidad de los Andes",
      "departamento": "Facultad de Economía",
      "areas_expertise": ["evaluación de impacto", "economía de la educación", "presupuesto público", "finanzas públicas"],
      "experiencia_convocatorias": ["MGA", "BID", "MINCIENCIAS"],
      "proyectos_anteriores": 9,
      "publicaciones_indexadas": 22,
      "idiomas": ["español", "inglés"],
      "disponibilidad": "tiempo_parcial",
      "email": "mfrios@uniandes.edu.co"
    },
    {
      "id": "INV006",
      "nombre": "Mg. Luis Carlos Bermúdez",
      "titulo": "Magíster en Gestión de Proyectos",
      "institucion": "Pontificia Universidad Javeriana",
      "departamento": "Facultad de Ingeniería Industrial",
      "areas_expertise": ["gerencia de proyectos", "marco lógico", "monitoreo y evaluación", "cooperación internacional"],
      "experiencia_convocatorias": ["ERASMUS", "ZOPP", "BID", "HORIZONTE"],
      "proyectos_anteriores": 14,
      "publicaciones_indexadas": 6,
      "idiomas": ["español", "inglés", "alemán"],
      "disponibilidad": "tiempo_completo",
      "email": "lcbermudez@javeriana.edu.co"
    },
    {
      "id": "INV007",
      "nombre": "Dra. Ana Milena Vargas",
      "titulo": "PhD en Salud Pública",
      "institucion": "Universidad CES",
      "departamento": "Escuela de Salud Pública",
      "areas_expertise": ["salud comunitaria", "poblaciones vulnerables", "equidad en salud", "género y desarrollo"],
      "experiencia_convocatorias": ["MINCIENCIAS", "BID", "ERASMUS"],
      "proyectos_anteriores": 7,
      "publicaciones_indexadas": 15,
      "idiomas": ["español", "inglés"],
      "disponibilidad": "tiempo_parcial",
      "email": "amvargas@ces.edu.co"
    },
    {
      "id": "INV008",
      "nombre": "Dr. Ricardo Emilio Pardo",
      "titulo": "PhD en Ciencias Políticas",
      "institucion": "Universidad Externado de Colombia",
      "departamento": "Facultad de Finanzas, Gobierno y Relaciones Internacionales",
      "areas_expertise": ["políticas públicas", "gobernanza", "descentralización", "relaciones internacionales"],
      "experiencia_convocatorias": ["BID", "ERASMUS", "HORIZONTE", "ZOPP"],
      "proyectos_anteriores": 10,
      "publicaciones_indexadas": 17,
      "idiomas": ["español", "inglés", "francés"],
      "disponibilidad": "tiempo_completo",
      "email": "repardo@uexternado.edu.co"
    },
    {
      "id": "INV009",
      "nombre": "Ing. Daniel Mateo Solarte",
      "titulo": "Especialista en IA y Cloud Computing",
      "institucion": "Google Cloud Partner Network",
      "departamento": "Arquitectura de Soluciones AI",
      "areas_expertise": ["google cloud platform", "vertex ai", "gemini api", "arquitecturas escalables", "transformación digital"],
      "experiencia_convocatorias": ["BID", "MINCIENCIAS", "GOOGLE.ORG", "VC FUND"],
      "proyectos_anteriores": 22,
      "publicaciones_indexadas": 5,
      "idiomas": ["español", "inglés"],
      "disponibilidad": "tiempo_completo",
      "email": "dsolarte@nexus-google.com"
    }
  ]
}